odoo/addons/base_field_deprecated/README.rst
odoo/addons/base_field_deprecated/__init__.py
odoo/addons/base_field_deprecated/__manifest__.py
odoo/addons/base_field_deprecated/hooks.py
odoo/addons/base_field_deprecated/i18n/base_field_deprecated.pot
odoo/addons/base_field_deprecated/models/__init__.py
odoo/addons/base_field_deprecated/models/ir_model_fields.py
odoo/addons/base_field_deprecated/readme/CONTRIBUTORS.rst
odoo/addons/base_field_deprecated/readme/DESCRIPTION.rst
odoo/addons/base_field_deprecated/readme/USAGE.rst
odoo/addons/base_field_deprecated/static/description/icon.png
odoo/addons/base_field_deprecated/static/description/index.html
odoo/addons/base_field_deprecated/views/ir_model_fields_views.xml
odoo_addon_base_field_deprecated-15.0.1.0.0.4.dist-info/METADATA
odoo_addon_base_field_deprecated-15.0.1.0.0.4.dist-info/WHEEL
odoo_addon_base_field_deprecated-15.0.1.0.0.4.dist-info/top_level.txt
odoo_addon_base_field_deprecated-15.0.1.0.0.4.dist-info/RECORD
